zyz/__init__.py
zyz/utils/__init__.py
zyz/utils/email.py
zyz/utils/os.py
zyz/zlog/__init__.py
zyz-0.2.3.dist-info/LICENSE
zyz-0.2.3.dist-info/METADATA
zyz-0.2.3.dist-info/WHEEL
zyz-0.2.3.dist-info/top_level.txt
zyz-0.2.3.dist-info/RECORD
